mercury_engine_data_structures/__init__.py
mercury_engine_data_structures/__main__.py
mercury_engine_data_structures/_dread_data_construct.py
mercury_engine_data_structures/base_resource.py
mercury_engine_data_structures/cli.py
mercury_engine_data_structures/common_types.py
mercury_engine_data_structures/crc.py
mercury_engine_data_structures/dread_data.py
mercury_engine_data_structures/dread_property_names.bin
mercury_engine_data_structures/dread_resource_names.bin
mercury_engine_data_structures/dread_types.json
mercury_engine_data_structures/file_tree_editor.py
mercury_engine_data_structures/game_check.py
mercury_engine_data_structures/object.py
mercury_engine_data_structures/pointer_set.py
mercury_engine_data_structures/py.typed
mercury_engine_data_structures/romfs.py
mercury_engine_data_structures/samus_returns_data.py
mercury_engine_data_structures/samus_returns_types.json
mercury_engine_data_structures/sr_property_names.bin
mercury_engine_data_structures/sr_property_names.json
mercury_engine_data_structures/sr_resource_names.bin
mercury_engine_data_structures/type_lib.py
mercury_engine_data_structures/version.py
mercury_engine_data_structures/version_validation.py
mercury_engine_data_structures/__pyinstaller/__init__.py
mercury_engine_data_structures/__pyinstaller/hook-mercury_engine_data_structures.py
mercury_engine_data_structures/adapters/__init__.py
mercury_engine_data_structures/adapters/enum_adapter.py
mercury_engine_data_structures/adapters/offset.py
mercury_engine_data_structures/construct_extensions/__init__.py
mercury_engine_data_structures/construct_extensions/alignment.py
mercury_engine_data_structures/construct_extensions/enum.py
mercury_engine_data_structures/construct_extensions/function_complex.py
mercury_engine_data_structures/construct_extensions/json.py
mercury_engine_data_structures/construct_extensions/misc.py
mercury_engine_data_structures/construct_extensions/strings.py
mercury_engine_data_structures/construct_extensions/version.py
mercury_engine_data_structures-0.35.0.dist-info/LICENSE
mercury_engine_data_structures-0.35.0.dist-info/METADATA
mercury_engine_data_structures-0.35.0.dist-info/WHEEL
mercury_engine_data_structures-0.35.0.dist-info/entry_points.txt
mercury_engine_data_structures-0.35.0.dist-info/top_level.txt
mercury_engine_data_structures-0.35.0.dist-info/RECORD
