Metadata-Version: 2.1
Name: mercury-engine-data-structures
Version: 0.35.0
Summary: Construct file definitions for the Mercury Engine, the in-house game engine from MercurySteam
Project-URL: Homepage, https://github.com/randovania/mercury-engine-data-structures
Classifier: License :: OSI Approved :: MIT License
Classifier: Development Status :: 3 - Alpha
Classifier: Intended Audience :: Developers
Classifier: Programming Language :: Python :: 3.10
Classifier: Programming Language :: Python :: 3.11
Classifier: Programming Language :: Python :: 3.12
Classifier: Programming Language :: Python :: 3.13
Requires-Python: >=3.10
License-File: LICENSE
Requires-Dist: construct>=2.10.70
Requires-Dist: randovania-lupa>=2.0.1
Requires-Dist: zstandard
Provides-Extra: test
Requires-Dist: pytest>=8.3.1; extra == "test"
Requires-Dist: pytest-cov; extra == "test"
